SortVisualization/BogoSort.py
SortVisualization/BubbleSort.py
SortVisualization/CountingSort.py
SortVisualization/InsertionSort.py
SortVisualization/LICENSE.md
SortVisualization/MiracleSort.py
SortVisualization/SelectionSort.py
SortVisualization/ShellSort.py
SortVisualization/__init__.py
SortVisualization/dark_moon.png
SortVisualization/light_moon.png
SortVisualization/main.py
SortVisualization/yellow_moon.png
SortingVisualizer/BogoSort.py
SortingVisualizer/BubbleSort.py
SortingVisualizer/CountingSort.py
SortingVisualizer/InsertionSort.py
SortingVisualizer/MiracleSort.py
SortingVisualizer/SelectionSort.py
SortingVisualizer/ShellSort.py
SortingVisualizer/__init__.py
SortingVisualizer/dark_moon.png
SortingVisualizer/light_moon.png
SortingVisualizer/main.py
SortingVisualizer/yellow_moon.png
SortVisualization-1.4.dist-info/METADATA
SortVisualization-1.4.dist-info/WHEEL
SortVisualization-1.4.dist-info/top_level.txt
SortVisualization-1.4.dist-info/RECORD
