Metadata-Version: 2.1
Name: SortVisualization
Version: 1.4
Project-URL: Repository, https://github.com/Andy1iang/Sorting_Algorithms
Requires-Dist: pygame
